arbok_driver/__init__.py
arbok_driver/abstract_readout.py
arbok_driver/arbok_driver.py
arbok_driver/device.py
arbok_driver/experiment.py
arbok_driver/generic_tunig_interface.py
arbok_driver/measurement.py
arbok_driver/parameter_types.py
arbok_driver/path_finders.py
arbok_driver/qua_helpers.py
arbok_driver/read_sequence.py
arbok_driver/sequence_base.py
arbok_driver/signal.py
arbok_driver/sqlalchemy_classes.py
arbok_driver/sub_sequence.py
arbok_driver/sweep.py
arbok_driver/utils.py
arbok_driver/measurement_runners/__init__.py
arbok_driver/measurement_runners/measurement_runner_base.py
arbok_driver/measurement_runners/native_measurement_runner.py
arbok_driver/measurement_runners/qcodes_measurement_runner.py
arbok_driver/parameters/__init__.py
arbok_driver/parameters/gettable_parameter.py
arbok_driver/parameters/gettable_parameter_base.py
arbok_driver/parameters/gettable_parameter_multi.py
arbok_driver/parameters/sequence_parameter.py
arbok_driver/tests/all_the_qua.py
arbok_driver/tests/conftest.py
arbok_driver/tests/dummy_opx_config.py
arbok_driver/tests/helpers.py
arbok_driver/tests/param_types_test.py
arbok_driver/tests/param_types_test2.py
arbok_driver/tests/sequence_params_test.py
arbok_driver/tests/sequence_reset_test.py
arbok_driver/tests/test_arbok_driver.py
arbok_driver/tests/test_measurement_sweep.py
arbok_driver/tests/test_measurement_sweep_parametrised_snake.py
arbok_driver/tests/test_sequence.py
arbok_driver/tests/test_sequence_parameter.py
arbok_driver/tests/test_sub_sequence.py
arbok_driver/tests/test_sweep.py
arbok_driver/tests/var_readout.py
arbok_driver/tests/var_readout_config.py
arbok_driver/tests/qm_config/opx1000.py
arbok_driver/tests/test_vectors/sweep_test.qua
arbok_driver-2.3.0.dist-info/licenses/LICENSE
arbok_driver-2.3.0.dist-info/METADATA
arbok_driver-2.3.0.dist-info/WHEEL
arbok_driver-2.3.0.dist-info/top_level.txt
arbok_driver-2.3.0.dist-info/RECORD
