Metadata-Version: 2.4
Name: arbok_driver
Version: 2.3.0
Summary: QCoDeS compatible driver for the OPX+ from Quantum Machines
Author-email: Andreas Nickl <a.nickl@unsw.edu.au>
License: BSD-3-Clause
Classifier: Programming Language :: Python :: 3.12
Requires-Python: >=3.12
License-File: LICENSE
Requires-Dist: anytree>=2.13
Requires-Dist: jupyterlab
Requires-Dist: numpy>=1.23
Requires-Dist: matplotlib
Requires-Dist: minio~=7.2
Requires-Dist: ipython
Requires-Dist: psycopg2-binary~=2.9
Requires-Dist: s3fs~=2025.10
Requires-Dist: scipy
Requires-Dist: SQLAlchemy~=2.0
Requires-Dist: qm-qua>=1.2.1
Requires-Dist: qcodes>=0.54.4
Requires-Dist: qualang_tools>=0.19
Requires-Dist: qcodes-contrib-drivers>=0.23
Requires-Dist: rich>=14.0
Requires-Dist: zarr~=2.18
Provides-Extra: docs
Requires-Dist: myst-nb; extra == "docs"
Requires-Dist: sphinx; extra == "docs"
Requires-Dist: sphinx-rtd-theme; extra == "docs"
Requires-Dist: sphinx-autodoc-typehints; extra == "docs"
Dynamic: license-file
